README.md
setup.py
saltant_cli/__init__.py
saltant_cli/config.py
saltant_cli/constants.py
saltant_cli/exceptions.py
saltant_cli/main.py
saltant_cli/version.py
saltant_cli.egg-info/PKG-INFO
saltant_cli.egg-info/SOURCES.txt
saltant_cli.egg-info/dependency_links.txt
saltant_cli.egg-info/entry_points.txt
saltant_cli.egg-info/requires.txt
saltant_cli.egg-info/top_level.txt
saltant_cli/subcommands/__init__.py
saltant_cli/subcommands/completion.py
saltant_cli/subcommands/resource.py
saltant_cli/subcommands/task_instances.py
saltant_cli/subcommands/task_queues.py
saltant_cli/subcommands/task_types.py
saltant_cli/subcommands/task_whitelists.py
saltant_cli/subcommands/users.py
saltant_cli/subcommands/utils.py